ai_django_core/__init__.py
ai_django_core/apps.py
ai_django_core/checks.py
ai_django_core/context_manager.py
ai_django_core/context_processors.py
ai_django_core/managers.py
ai_django_core/models.py
ai_django_core/admin/__init__.py
ai_django_core/admin/model_admins/__init__.py
ai_django_core/admin/model_admins/classes.py
ai_django_core/admin/model_admins/inlines.py
ai_django_core/admin/model_admins/mixins.py
ai_django_core/admin/views/__init__.py
ai_django_core/admin/views/forms.py
ai_django_core/admin/views/mixins.py
ai_django_core/drf/__init__.py
ai_django_core/drf/fields.py
ai_django_core/drf/serializers.py
ai_django_core/drf/tests.py
ai_django_core/gitlab/__init__.py
ai_django_core/gitlab/coverage.py
ai_django_core/graphql/__init__.py
ai_django_core/graphql/forms/__init__.py
ai_django_core/graphql/forms/mutations.py
ai_django_core/graphql/schemes/__init__.py
ai_django_core/graphql/schemes/mutations.py
ai_django_core/graphql/sentry/__init__.py
ai_django_core/graphql/sentry/utils.py
ai_django_core/graphql/sentry/views.py
ai_django_core/graphql/tests/__init__.py
ai_django_core/graphql/tests/base_test.py
ai_django_core/locale/de/LC_MESSAGES/django.mo
ai_django_core/locale/de/LC_MESSAGES/django.po
ai_django_core/mail/__init__.py
ai_django_core/mail/errors.py
ai_django_core/mail/backends/__init__.py
ai_django_core/mail/backends/whitelist_smtp.py
ai_django_core/mail/services/__init__.py
ai_django_core/mail/services/base.py
ai_django_core/mail/services/tests.py
ai_django_core/management/__init__.py
ai_django_core/management/commands/__init__.py
ai_django_core/management/commands/validate_test_structure.py
ai_django_core/middleware/__init__.py
ai_django_core/middleware/current_user.py
ai_django_core/mixins/__init__.py
ai_django_core/mixins/bleacher.py
ai_django_core/mixins/models.py
ai_django_core/mixins/validation.py
ai_django_core/selectors/__init__.py
ai_django_core/selectors/base.py
ai_django_core/selectors/permission.py
ai_django_core/sentry/__init__.py
ai_django_core-7.0.2.dist-info/LICENSE.md
ai_django_core-7.0.2.dist-info/WHEEL
ai_django_core-7.0.2.dist-info/METADATA
ai_django_core-7.0.2.dist-info/RECORD
