Metadata-Version: 2.1
Name: ai-django-core
Version: 7.0.2
Summary: Ambient toolbox - Lots of helper functions and useful widgets
Author-email: "Ambient Innovation: GmbH" <hello@ambient.digital>
Classifier: Development Status :: 5 - Production/Stable
Classifier: Environment :: Web Environment
Classifier: Framework :: Django
Classifier: Framework :: Django :: 2.2
Classifier: Framework :: Django :: 3.1
Classifier: Framework :: Django :: 3.2
Classifier: Framework :: Django :: 4.0
Classifier: Framework :: Django :: 4.1
Classifier: Intended Audience :: Developers
Classifier: License :: OSI Approved :: MIT License
Classifier: Natural Language :: English
Classifier: Operating System :: OS Independent
Classifier: Programming Language :: Python
Classifier: Programming Language :: Python :: 3
Classifier: Programming Language :: Python :: 3.8
Classifier: Programming Language :: Python :: 3.9
Classifier: Programming Language :: Python :: 3.10
Classifier: Programming Language :: Python :: 3.11
Classifier: Topic :: Utilities
Requires-Dist: Django>=2.2.28
Requires-Dist: bleach>=1.4,<6
Requires-Dist: python-dateutil>=2.5.3
Requires-Dist: html2text>=2020.1.16
Requires-Dist: freezegun ; extra == "dev"
Requires-Dist: gevent ; extra == "dev"
Requires-Dist: pre-commit ; extra == "dev"
Requires-Dist: pytest-cov ; extra == "dev"
Requires-Dist: pytest-django ; extra == "dev"
Requires-Dist: pytest-mock ; extra == "dev"
Requires-Dist: sphinx==4.2.0 ; extra == "docs"
Requires-Dist: sphinx-rtd-theme==1.0.0 ; extra == "docs"
Requires-Dist: m2r2==0.3.1 ; extra == "docs"
Requires-Dist: mistune<2.0.0 ; extra == "docs"
Requires-Dist: djangorestframework>=3.8.2 ; extra == "drf"
Requires-Dist: graphene-django>=2.2.0 ; extra == "graphql"
Requires-Dist: django-graphql-jwt>=0.2.1 ; extra == "graphql"
Requires-Dist: django-crispy-forms>=1.4.0 ; extra == "view-layer"
Project-URL: Bugtracker, https://github.com/ambient-innovation/ai-django-core/issues
Project-URL: Changelog, https://ai-django-core.readthedocs.io/en/latest/features/changelog.html
Project-URL: Documentation, https://ai-django-core.readthedocs.io/en/latest/index.html
Project-URL: Maintained by, https://ambient.digital/
Provides-Extra: dev
Provides-Extra: docs
Provides-Extra: drf
Provides-Extra: graphql
Provides-Extra: view-layer
